LICENSE
MANIFEST.in
PKG-INFO
README.md
VERSION
pyproject.toml
setup.cfg
setup.py
docs/.readthedocs.yaml
docs/.rtd_environment.yaml
docs/Makefile
docs/README.md
docs/notebooks/DR Spectrometer Tutorial.ipynb
docs/notebooks/DRX Tutorial.ipynb
docs/notebooks/General Tutorial.ipynb
docs/notebooks/LDP Tutorial.ipynb
docs/notebooks/MCS Metadata Tutorial.ipynb
docs/notebooks/SDF Generation.ipynb
docs/notebooks/TBW & TBN Tutorial.ipynb
docs/source/astro.rst
docs/source/beamformer.rst
docs/source/busy.rst
docs/source/c-extensions.rst
docs/source/catalog.rst
docs/source/color.rst
docs/source/conf.py
docs/source/config.rst
docs/source/correlator.rst
docs/source/data-formats.rst
docs/source/dedispersion.rst
docs/source/fakedata.rst
docs/source/idf.rst
docs/source/imaging.rst
docs/source/index.rst
docs/source/install.rst
docs/source/kurtosis.rst
docs/source/lwa_user.rst
docs/source/mathutils.rst
docs/source/misc.rst
docs/source/observations.rst
docs/source/paths.rst
docs/source/progress.rst
docs/source/readers.rst
docs/source/robust.rst
docs/source/scripts.rst
docs/source/sdf.rst
docs/source/spectra.rst
docs/source/station.rst
docs/source/supplement.py
docs/source/swarm.rst
docs/source/transform.rst
docs/source/writers.rst
lsl/__init__.py
lsl/astro.py
lsl/catalog.py
lsl/config.py
lsl/skymap.py
lsl/testing.py
lsl/transform.py
lsl.egg-info/PKG-INFO
lsl.egg-info/SOURCES.txt
lsl.egg-info/dependency_links.txt
lsl.egg-info/not-zip-safe
lsl.egg-info/requires.txt
lsl.egg-info/top_level.txt
lsl/common/__init__.py
lsl/common/_metabundle_utils.py
lsl/common/_sdf_utils.py
lsl/common/adp.py
lsl/common/busy.py
lsl/common/color.py
lsl/common/data_access.py
lsl/common/dp.py
lsl/common/fir.cpp
lsl/common/idf.py
lsl/common/mcs.py
lsl/common/mcsADP.py
lsl/common/mcsNDP.py
lsl/common/metabundle.py
lsl/common/metabundleADP.py
lsl/common/metabundleDP.py
lsl/common/metabundleNDP.py
lsl/common/ndp.py
lsl/common/paths.py
lsl/common/progress.py
lsl/common/sdf.py
lsl/common/sdfADP.py
lsl/common/sdfNDP.py
lsl/common/sdmADP.py
lsl/common/sdmDP.py
lsl/common/sdmNDP.py
lsl/common/stations.py
lsl/correlator/__init__.py
lsl/correlator/blas.hpp
