Metadata-Version: 2.4
Name: lsl
Version: 3.0.7
Summary: LWA Software Library
Home-page: https://github.com/lwa-project/lsl
Author: Jayce Dowell
Author-email: jdowell@unm.edu
License: GPL
Classifier: Development Status :: 5 - Production/Stable
Classifier: Intended Audience :: Developers
Classifier: Intended Audience :: Science/Research
Classifier: License :: OSI Approved :: GNU General Public License (GPL)
Classifier: Topic :: Scientific/Engineering :: Astronomy
Classifier: Programming Language :: Python :: 3
Classifier: Programming Language :: Python :: 3.8
Classifier: Programming Language :: Python :: 3.9
Classifier: Programming Language :: Python :: 3.10
Classifier: Programming Language :: Python :: 3.11
Classifier: Programming Language :: Python :: 3.12
Classifier: Operating System :: MacOS :: MacOS X
Classifier: Operating System :: POSIX :: Linux
Requires-Python: >=3.8
License-File: LICENSE
Requires-Dist: astropy>=5.2
Requires-Dist: jplephem
Requires-Dist: healpy
Requires-Dist: h5py
Requires-Dist: numpy>=1.7
Requires-Dist: scipy>=0.19
Requires-Dist: ephem>=3.7.5.3
Requires-Dist: aipy>=3.0.1
Requires-Dist: pytz>=2012c
Dynamic: author
Dynamic: author-email
Dynamic: classifier
Dynamic: description
Dynamic: home-page
Dynamic: license
Dynamic: license-file
Dynamic: requires-dist
Dynamic: requires-python
Dynamic: summary
